{"stories":[[{"intent":"sdasa"},{"action":"sdsadasas"},{"slot":{"fares":"fares1"}},{"action":"asdfasdfas"},{"intent":"sdsads"},{"action":"asdfasdfas"}]],"rasa_nlu_data":{"common_examples":[{"intent":"sdsads","text":"asdasdasda"},{"intent":"sdsads","text":"sadasdassad"},{"intent":"sdasa","text":"sadasda"},{"intent":"sdasa","text":"asdasdasad"}],"regex_features":[],"lookup_tables":[],"entity_synonyms":[]},"actions":{"asdfasdfas":{"text":["fdasfasfasfasfsdf  {fares}"],"buttons":[{"text":"sdfasfasfasf","value":"fares1","slot":"fares"},{"text":"sfasfasf","value":"asfasfas","slot":"sdfasf"}]},"sdsadasas":{"text":["sdasda"],"buttons":[]},"eqfdfdf":{"text":["Fares :))"],"buttons":[]}},"slots":[{"name":"fares","type":"categorical","values":["fares1","fares2","fares3","fares5"]},{"name":"sdfasf","type":"text"},{"name":"sdfasfdsdf","type":"text"},{"name":"b7b_omk_awy","type":"bool"},{"name":"mins","type":"float"}]}